grammpy/__init__.py
grammpy/exceptions/CannotConvertException.py
grammpy/exceptions/CantCreateSingleRuleException.py
grammpy/exceptions/GrammpyException.py
grammpy/exceptions/LLParsingException.py
grammpy/exceptions/MultipleDefinitionException.py
grammpy/exceptions/NoRuleForLookAheadException.py
grammpy/exceptions/NonterminalDoesNotExistsException.py
grammpy/exceptions/NonterminalIsMissingException.py
grammpy/exceptions/NotASingleSymbolException.py
grammpy/exceptions/NotNonterminalException.py
grammpy/exceptions/NotParsedException.py
grammpy/exceptions/NotRuleException.py
grammpy/exceptions/ParsingAmbiguityException.py
grammpy/exceptions/ParsingException.py
grammpy/exceptions/ParsingTableDiscrepancyException.py
grammpy/exceptions/RuleException.py
grammpy/exceptions/RuleNotDefinedException.py
grammpy/exceptions/RuleSyntaxException.py
grammpy/exceptions/StartSymbolNotSetException.py
grammpy/exceptions/TerminalDoesNotExistsException.py
grammpy/exceptions/TreeDeletedException.py
grammpy/exceptions/UselessEpsilonException.py
grammpy/exceptions/__init__.py
grammpy/old_api/Grammar.py
grammpy/old_api/__init__.py
grammpy/old_api/_support.py
grammpy/parsers/__init__.py
grammpy/parsers/CYK/Field.py
grammpy/parsers/CYK/PlaceItem.py
grammpy/parsers/CYK/__init__.py
grammpy/parsers/CYK/cyk.py
grammpy/parsers/LL/__init__.py
grammpy/parsers/LL/create_ll_parsing_table.py
grammpy/parsers/LL/ll.py
grammpy/representation/Grammar.py
grammpy/representation/Nonterminal.py
grammpy/representation/Rule.py
grammpy/representation/Terminal.py
grammpy/representation/__init__.py
grammpy/representation/support/SplitRule.py
grammpy/representation/support/_BaseSet.py
grammpy/representation/support/_MetaRule.py
grammpy/representation/support/_NonterminalSet.py
grammpy/representation/support/_RuleConnectable.py
grammpy/representation/support/_RulesSet.py
grammpy/representation/support/_TerminalSet.py
grammpy/representation/support/_WeakList.py
grammpy/representation/support/__init__.py
grammpy-2.1.1.dist-info/LICENSE
grammpy-2.1.1.dist-info/METADATA
grammpy-2.1.1.dist-info/WHEEL
grammpy-2.1.1.dist-info/top_level.txt
grammpy-2.1.1.dist-info/RECORD
