Metadata-Version: 2.1
Name: grammpy
Version: 2.1.1
Summary: Parsing library with all required tools to parse context-free grammars.
Home-page: https://github.com/PatrikValkovic/grammpy
Download-URL: https://github.com/PatrikValkovic/grammpy/archive/v2.1.1.tar.gz
Author: Patrik Valkovic
Author-email: patrik.valkovic@hotmail.cz
License: The MIT License
License-File: LICENSE
Requires-Dist: typing
Requires-Dist: deprecated
